shellexecute/__init__.py
shellexecute-1.0.5.dist-info/LICENSE
shellexecute-1.0.5.dist-info/METADATA
shellexecute-1.0.5.dist-info/WHEEL
shellexecute-1.0.5.dist-info/top_level.txt
shellexecute-1.0.5.dist-info/RECORD
