Metadata-Version: 2.1
Name: shellexecute
Version: 1.0.5
Summary: Executes a command, allows confirmation to be sent using p/wexpect
Home-page: https://github.com/zackees/shellexecute
Maintainer: Zachary Vorhies
License: BSD 3-Clause License
Keywords: template-python-cmd
Classifier: Programming Language :: Python :: 3
Requires-Python: >=3.7
License-File: LICENSE
Requires-Dist: colorama
Requires-Dist: pexpect ; sys_platform != "win32"
Requires-Dist: pywin32 ; sys_platform == "win32"
Requires-Dist: wexpect ; sys_platform == "win32"
